jsoncontrast/Contrast_Json.py
jsoncontrast/Gen_Csv.py
jsoncontrast/__init__.py
jsoncontrast-1.0.0.dist-info/LICENSE
jsoncontrast-1.0.0.dist-info/METADATA
jsoncontrast-1.0.0.dist-info/WHEEL
jsoncontrast-1.0.0.dist-info/top_level.txt
jsoncontrast-1.0.0.dist-info/RECORD
