Metadata-Version: 2.1
Name: jsoncontrast
Version: 1.0.0
Summary: To contrast two json
Home-page: https://github.com/sophialjm/jsoncontrast
Author: Lijianmei
Author-email: sophialjm@qq.com
License: UNKNOWN
Platform: UNKNOWN
Classifier: Programming Language :: Python :: 3
Classifier: License :: OSI Approved :: MIT License
Classifier: Operating System :: OS Independent
